aiogt/__init__.py
aiogt/cache/__init__.py
aiogt/cache/cache.py
aiogt/cache/storage/__init__.py
aiogt/cache/storage/base.py
aiogt/cache/storage/memory_storage.py
aiogt/enums.py
aiogt/translaitor.py
aiogt/transport/__init__.py
aiogt/transport/aiohttp_t.py
aiogt/transport/base.py
aiogt/transport/httpx_t.py
aiogt/utils.py
aiogt-1.0.0.post1.dist-info/METADATA
aiogt-1.0.0.post1.dist-info/WHEEL
aiogt-1.0.0.post1.dist-info/RECORD
