Metadata-Version: 2.1
Name: aiogt
Version: 1.0.0.post1
Summary: 
Author: Robert Stoul
Author-email: rekiiky@proton.me
Requires-Python: >=3.11,<4.0
Classifier: Programming Language :: Python :: 3
Classifier: Programming Language :: Python :: 3.11
Provides-Extra: aiohttp
Provides-Extra: cache
Provides-Extra: httpx
Requires-Dist: aiohttp (>=3.8.6,<4.0.0) ; extra == "aiohttp"
Requires-Dist: httpx (>=0.25.1,<0.26.0) ; extra == "httpx"
Requires-Dist: redis (>=5.0.1,<6.0.0) ; extra == "cache"
Requires-Dist: urlcon (>=1.0.0,<2.0.0)
